pxpy/__init__.py
pxpy/functions.py
pxpy/pxonnx.py
pxpy/pxpy_environ
pxpy/data/sin44
pxpy/lib/FILES
pxpy/lib/libpx.dll
pxpy/lib/libpx.so
pxpy/lib/libpx_aarch64.so
pxpy/lib/libpx_aarch64_dbg.so
pxpy/lib/libpx_aarch64_ext_culbp.so
pxpy/lib/libpx_dbg.so
pxpy/lib/libpx_ext_culbp.so
pxpy/test/__init__.py
pxpy/test/test_core.py
pxpy/tools/__init__.py
pxpy-1.0a71.dist-info/LICENSE
pxpy-1.0a71.dist-info/METADATA
pxpy-1.0a71.dist-info/WHEEL
pxpy-1.0a71.dist-info/top_level.txt
pxpy-1.0a71.dist-info/RECORD
