Metadata-Version: 2.1
Name: pxpy
Version: 1.0a71
Summary: discrete pairwise undirected graphical models
Home-page: https://www.randomfields.org/px
Author: Nico Piatkowski
Author-email: nico.piatkowski@gmail.com
License: UNKNOWN
Platform: UNKNOWN
Classifier: Development Status :: 3 - Alpha
Classifier: Intended Audience :: Science/Research
Classifier: Programming Language :: Python :: 3
Classifier: License :: Free for non-commercial use
Classifier: Operating System :: POSIX :: Linux
Classifier: Operating System :: Microsoft :: Windows
Classifier: Topic :: Scientific/Engineering :: Artificial Intelligence
Requires-Python: >=3.6
License-File: LICENSE
Requires-Dist: numpy
